pycricketr/__init__.py
pycricketr/analytics.py
pycricketr-0.0.9.dist-info/LICENSE.txt
pycricketr-0.0.9.dist-info/METADATA
pycricketr-0.0.9.dist-info/WHEEL
pycricketr-0.0.9.dist-info/top_level.txt
pycricketr-0.0.9.dist-info/RECORD
