Metadata-Version: 2.1
Name: pycricketr
Version: 0.0.9
Summary: Analyze Cricketers Based on ESPN Cricinfo Statsguru
Home-page: https://github.com/tvganesh/pycricketr
Author: Tinniam V Ganesh
Author-email: tvganesh.85@gmail.com
License: UNKNOWN
Platform: UNKNOWN
Classifier: Programming Language :: Python :: 3
Classifier: License :: OSI Approved :: MIT License
Classifier: Operating System :: OS Independent
